Tarea1/probador.v
module probador( // Módulo probador: generador de señales y monitor de datos
	input		sAlr_estr,
	input		sAlr_cond,
	output reg	sLuz,
	output reg	sPrta,
	output reg	sIgn);

	reg 		clk;
	// Bloque de procedimiento, no sintetizable, se recorre una única vez
	// Generalmente, los initial sólo se usan en los testbench o probadores
	// Se recomienda siempre sincronizar con el reloj y utilizar
	// asignaciones no bloqueantes en la generación de señales
	initial begin
		$dumpfile("alarma.vcd");	// Nombre de archivo del "dump"
		$dumpvars;			// Directiva para "dumpear" variables
		// Mensaje que se imprime en consola una vez
		$display ("\t\t\tclk,\tsAlr_estr,\tsAlr_cond,\tsLuz,\tsPrta,\tsIgn");
		// Mensaje que se imprime en consola cada vez que un elemento de la lista cambia
		$monitor($time,"\t%b\t%b\t\t%b\t\t%b\t%b\t%b", clk, sAlr_estr, sAlr_cond, sLuz, sPrta, sIgn);
		{sLuz, sPrta, sIgn} = 3'b0; 	// A los 3 bits, asigna un tipo bit con valor 0.
		repeat (8) begin		// Repite 8 veces
								// Es muy importante la notación de sincronizar con @(posedge clk); y luego,
								// hacer una asignación no bloqueante ( <= ), les va a ahorrar tiempo. 
        		@(posedge clk);	// Espera/sincroniza con el flanco positivo del reloj
			{sLuz, sPrta, sIgn} <= {sLuz, sPrta, sIgn} + 1; // Suma 1, asignación no bloqueante 
		end
		@(posedge clk);	
		{sLuz, sPrta, sIgn} <= 'b0;	// Asigna un tipo bit con valor 0, de tamaño N
		$finish;			// Termina de almacenar señales
	end
	// Reloj
	initial	clk 	<= 0;			// Valor inicial al reloj, sino siempre será indeterminado
	always	#2 clk 	<= ~clk;		// Hace "toggle" cada 2*10ns
endmodule

Tarea1/alarma.vcd
$date
	Mon Aug 30 12:03:29 2021
$end
$version
	Icarus Verilog
$end
$timescale
	1s
$end
$scope module probador $end
$var wire 1 ! sAlr_cond $end
$var wire 1 " sAlr_estr $end
$var reg 1 # clk $end
$var reg 1 $ sIgn $end
$var reg 1 % sLuz $end
$var reg 1 & sPrta $end
$upscope $end
$enddefinitions $end
#0
$dumpvars
0&
0%
0$
0#
z"
z!
$end
#2
1$
1#
#4
0#
#6
1&
0$
1#
#8
0#
#10
1$
1#
#12
0#
#14
1%
0&
0$
1#
#16
0#
#18
1$
1#
#20
0#
#22
1&
0$
1#
#24
0#
#26
1$
1#
#28
0#
#30
0%
0&
0$
1#
