Tarea2/muxtest.v
module muxtest(
    input      [1:0] data_out,
    output reg clk,//       estimilar salidas
    output reg reset_L,
    output reg selector,
    output reg [1:0] data_in0,//    estimular salidas
    output reg [1:0] data_in1
);
initial begin
    $dumpfile("muxsignal.vcd");	// Nombre de .vcd a graficar
	$dumpvars;
    //$display ("\t\t\tclk,\tout,\treset,\tselector,\tin0,\tin1");
    $monitor("t=",$time,"clk=%b,data_out=%b,\t\t%b\t\t%b\t%b\t%b", clk,data_out,selector,reset_L,data_in0,data_in1);
    reset_L=0;    //valor por defecto de entrada selector
    selector=0;
    {data_in0,data_in1}= 2'b00; //valor inicial de datos de entradas
    repeat (1) begin //Vamos a repetirlo 3 ciclos
        @(posedge clk);
        reset_L<=1;
        selector<=0;
    end 
        @(posedge clk)
        data_in0 <= 2'b11;
		data_in1 <= 2'b10;
		
        @(posedge clk)
        data_in0 <= 2'b01;
		data_in1 <= 2'b00;
        selector <= 1;
        
        @(posedge clk)
        data_in0 <= 2'b00;
		data_in1 <= 2'b10;
        
        @(posedge clk)
        data_in0 <= 2'b11;
		data_in1 <= 2'b11;
        selector <= 0;
        
        @(posedge clk)
        data_in0 <= 2'b00;
		data_in1 <= 2'b01;
        selector <= 1;

        @(posedge clk)
        data_in0 <= 2'b10;
		data_in1 <= 2'b00;
        selector <= 0;

		@(posedge clk)
        selector <= 1;

		@(posedge clk)
        data_in0 <= 2'b10;
		data_in1 <= 2'b00;
        selector <= 1;

		$finish;
    end
    // Reloj
	initial	clk 	<= 0;			// Valor inicial al relo
	always	#2 clk 	<= ~clk;		//invertido cada 2*10ns
endmodule

Tarea2/mux_conductual.v
module mux_conductual(
    input clk,
    input reset_L,
    input selector,//bit de seleccion
    input [1:0] data_in0,//entradad de datos 0
    input [1:0] data_in1,//entrada de datos 1
    output reg [1:0] data_out//salida como bus de dos bits
);
always@(posedge clk) //funcionamineto como flip-flop dincronizado por flanco positivo de reloj
            begin
                if (reset_L==1) //si el selector esta en 1, el mux de en medio funciona como buffer hasta el flip-flop
                    if(selector==0)
                        data_out<=data_in0; //aaignacion no bloqueante
                    else
                        data_out<=data_in1;
                else if(reset_L==0) //segun enunciado, en este caso, el mux dos estara con su salida en 0
                data_out<=2'b00; 
            end
endmodule

Tarea2/Banco.v
`timescale 1s/1s
`include "mux_conductual.v"
`include "muxtest.v"
module BancoPruebas;
    wire clk;
    wire reset_L;
    wire selector;
    wire [1:0] data_in0;
    wire [1:0] data_in1;
    wire [1:0] data_out;
    mux_conductual mux_(/*AUTOINST*/
			// Outputs
			.data_out	(data_out[1:0]),
			// Inputs
			.clk		(clk),
			.reset_L	(reset_L),
			.selector	(selector),
			.data_in0	(data_in0[1:0]),
			.data_in1	(data_in1[1:0]));
    muxtest test_(/*AUTOINST*/
		  // Outputs
		  .clk			(clk),
		  .reset_L		(reset_L),
		  .selector		(selector),
		  .data_in0		(data_in0[1:0]),
		  .data_in1		(data_in1[1:0]),
		  // Inputs
		  .data_out		(data_out[1:0]));
endmodule

Tarea2/muxsignal.vcd
$date
	Tue Aug 31 17:49:15 2021
$end
$version
	Icarus Verilog
$end
$timescale
	1s
$end
$scope module BancoPruebas $end
$var wire 1 ! selector $end
$var wire 1 " reset_L $end
$var wire 2 # data_out [1:0] $end
$var wire 2 $ data_in1 [1:0] $end
$var wire 2 % data_in0 [1:0] $end
$var wire 1 & clk $end
$scope module mux_ $end
$var wire 1 ! selector $end
$var wire 1 " reset_L $end
$var wire 2 ' data_in1 [1:0] $end
$var wire 2 ( data_in0 [1:0] $end
$var wire 1 & clk $end
$var reg 2 ) data_out [1:0] $end
$upscope $end
$scope module test_ $end
$var wire 2 * data_out [1:0] $end
$var reg 1 & clk $end
$var reg 2 + data_in0 [1:0] $end
$var reg 2 , data_in1 [1:0] $end
$var reg 1 " reset_L $end
$var reg 1 ! selector $end
$upscope $end
$upscope $end
$enddefinitions $end
#0
$dumpvars
b0 ,
b0 +
bx *
bx )
b0 (
b0 '
0&
b0 %
b0 $
bx #
0"
0!
$end
#2
b0 #
b0 )
b0 *
1"
1&
#4
0&
#6
b10 $
b10 '
b10 ,
b11 %
b11 (
b11 +
1&
#8
0&
#10
b11 #
b11 )
b11 *
1!
b0 $
b0 '
b0 ,
b1 %
b1 (
b1 +
1&
#12
0&
#14
b10 $
b10 '
b10 ,
b0 %
b0 (
b0 +
b0 #
b0 )
b0 *
1&
#16
0&
#18
b10 #
b10 )
b10 *
0!
b11 $
b11 '
b11 ,
b11 %
b11 (
b11 +
1&
#20
0&
#22
1!
b1 $
b1 '
b1 ,
b0 %
b0 (
b0 +
b11 #
b11 )
b11 *
1&
#24
0&
#26
b1 #
b1 )
b1 *
0!
b0 $
b0 '
b0 ,
b10 %
b10 (
b10 +
1&
#28
0&
#30
1!
b10 #
b10 )
b10 *
1&
#32
0&
#34
b0 #
b0 )
b0 *
1&
